MANIFEST.in
README.md
requirements.txt
setup.py
roboduck/__init__.py
roboduck/config.py
roboduck/debug.py
roboduck/decorators.py
roboduck/errors.py
roboduck/ipy_utils.py
roboduck/logging.py
roboduck/magic.py
roboduck/utils.py
roboduck.egg-info/PKG-INFO
roboduck.egg-info/SOURCES.txt
roboduck.egg-info/dependency_links.txt
roboduck.egg-info/entry_points.txt
roboduck.egg-info/requires.txt
roboduck.egg-info/top_level.txt
roboduck/cli/__init__.py
roboduck/cli/cli.py
roboduck/langchain/__init__.py
roboduck/langchain/callbacks.py
roboduck/langchain/chat.py
roboduck/langchain/utils.py
roboduck/prompts/__init__.py
roboduck/prompts/utils.py
roboduck/prompts/chat/__template__.yaml
roboduck/prompts/chat/debug.yaml
roboduck/prompts/chat/debug_full.yaml
roboduck/prompts/chat/debug_full_stack_trace.yaml
roboduck/prompts/chat/debug_stack_trace.yaml