Metadata-Version: 2.1
Name: roboduck
Version: 0.10.1
Summary: A natural language debugger.
Author: Harrison Mamin
Author-email: harrisonmamin@gmail.com
Project-URL: Documentation, https://hdmamin.github.io/roboduck/
Project-URL: Repository, https://github.com/hdmamin/roboduck
Keywords: debugging,llm,language model,dev tools,errors,jupyter magic,gpt,openai,langchain
Requires-Python: >=3.8
Requires-Dist: IPython==7.25.0
Requires-Dist: colorama>=0.3.0
Requires-Dist: ipynbname==2021.3.2
Requires-Dist: langchain==0.0.118
Requires-Dist: openai==0.27.*
